vbbpy/__init__.py
vbbpy/connections.py
vbbpy/departure.py
vbbpy/journey.py
vbbpy/leg.py
vbbpy/line.py
vbbpy/location.py
vbbpy/modes.py
vbbpy/station.py
vbbpy/vbbHelper.py
vbbpy-1.1.8.data/scripts/vbbpy-addressRouting
vbbpy-1.1.8.data/scripts/vbbpy-showDepartures
vbbpy-1.1.8.data/scripts/vbbpy-stationId
vbbpy-1.1.8.data/scripts/vbbpy-stationInformation
vbbpy-1.1.8.dist-info/LICENSE
vbbpy-1.1.8.dist-info/METADATA
vbbpy-1.1.8.dist-info/WHEEL
vbbpy-1.1.8.dist-info/top_level.txt
vbbpy-1.1.8.dist-info/RECORD
