Metadata-Version: 2.1
Name: vbbpy
Version: 1.1.8
Summary: A python wrapper for the VBB REST-API by derhuerst
Download-URL: https://github.com/Colum31/vbb-pythonWrapper
Author: colum31
License: MIT
Requires-Python: >3.6
License-File: LICENSE
Requires-Dist: requests
Requires-Dist: datetime
Requires-Dist: geopy
